ezspreadsheet.py
ezspreadsheet-0.2.2.dist-info/LICENSE
ezspreadsheet-0.2.2.dist-info/METADATA
ezspreadsheet-0.2.2.dist-info/WHEEL
ezspreadsheet-0.2.2.dist-info/top_level.txt
ezspreadsheet-0.2.2.dist-info/RECORD
