Metadata-Version: 2.1
Name: ezspreadsheet
Version: 0.2.2
Summary: A simple API to store/load python objects to/from spreadsheets
Home-page: UNKNOWN
Author: Kieran Wood
Author-email: kieran@canadiancoding.ca
License: UNKNOWN
Project-URL: API Docs, https://kieranwood.ca/ezspreadsheet
Project-URL: Source, https://github.com/Descent098/ezspreadsheet
Project-URL: Bug Report, https://github.com/Descent098/ezspreadsheet/issues/new?assignees=Descent098&labels=bug&template=bug_report.md&title=%5BBUG%5D
Project-URL: Feature Request, https://github.com/Descent098/ezspreadsheet/issues/new?assignees=Descent098&labels=enhancement&template=feature_request.md&title=%5BFeature%5D
Project-URL: Roadmap, https://github.com/Descent098/ezspreadsheet/projects
Platform: UNKNOWN
Classifier: Programming Language :: Python :: 3
Classifier: Operating System :: OS Independent
Classifier: Development Status :: 4 - Beta
Requires-Dist: openpyxl
Requires-Dist: colored
Provides-Extra: dev
Requires-Dist: nox ; extra == 'dev'
Requires-Dist: pytest ; extra == 'dev'
